AUTHORS.rst
CONTRIBUTING.rst
HISTORY.rst
LICENSE
MANIFEST.in
README.rst
setup.cfg
setup.py
docs/Makefile
docs/authors.rst
docs/conf.py
docs/contributing.rst
docs/history.rst
docs/index.rst
docs/installation.rst
docs/make.bat
docs/readme.rst
docs/usage.rst
nwt/__init__.py
nwt/__main__.py
nwt.egg-info/PKG-INFO
nwt.egg-info/SOURCES.txt
nwt.egg-info/dependency_links.txt
nwt.egg-info/entry_points.txt
nwt.egg-info/not-zip-safe
nwt.egg-info/requires.txt
nwt.egg-info/top_level.txt
nwt/controllers/__init__.py
nwt/controllers/cli.py
nwt/controllers/core.py
nwt/controllers/error.py
nwt/controllers/setup.py
nwt/models/__init__.py
nwt/models/config.py
nwt/models/epuber.py
nwt/views/__init__.py
nwt/views/console/__init__.py
nwt/views/console/command.py
nwt/views/console/printer.py
nwt/views/web/__init__.py
tests/__init__.py
tests/test_view_console_printer.py