Metadata-Version: 1.2
Name: nwt
Version: 0.1.2
Summary: Bible new world translation
Home-page: https://github.com/Unviray/nwt
Author: Unviray
Author-email: unviray@gmail.com
License: MIT license
Keywords: nwt bible
Platform: UNKNOWN
Classifier: Development Status :: 2 - Pre-Alpha
Classifier: Intended Audience :: Developers
Classifier: License :: OSI Approved :: MIT License
Classifier: Natural Language :: English
Classifier: Programming Language :: Python :: 3.6
Classifier: Programming Language :: Python :: 3.7
Requires-Python: >=3.6
